pyslack-0.5.0.dist-info/METADATA
pyslack-0.5.0.dist-info/RECORD
pyslack-0.5.0.dist-info/WHEEL
pyslack-0.5.0.dist-info/top_level.txt
slack/__init__.py
slack/auth.py
slack/channels.py
slack/chat.py
slack/exception.py
slack/files.py
slack/groups.py
slack/http_client.py
slack/im.py
slack/search.py
slack/stars.py
slack/users.py
