Metadata-Version: 2.1
Name: pyslack
Version: 0.5.0
Summary: Slack API Client
Home-page: https://github.com/kn/slack
Author: Katsuya Noguchi
Author-email: katsuya.noguchi@gmail.com
License: MIT
Platform: UNKNOWN
